chatdocs/__init__.py
chatdocs/__main__.py
chatdocs/add.py
chatdocs/chains.py
chatdocs/chat.py
chatdocs/config.py
chatdocs/download.py
chatdocs/embeddings.py
chatdocs/llms.py
chatdocs/logger.py
chatdocs/main.py
chatdocs/ui.py
chatdocs/utils.py
chatdocs/vectorstores.py
chatdocs/data/chatdocs.yml
chatdocs/data/index.html
chatdocs-0.2.6.dist-info/LICENSE
chatdocs-0.2.6.dist-info/METADATA
chatdocs-0.2.6.dist-info/WHEEL
chatdocs-0.2.6.dist-info/entry_points.txt
chatdocs-0.2.6.dist-info/top_level.txt
chatdocs-0.2.6.dist-info/RECORD
