Metadata-Version: 2.1
Name: chatdocs
Version: 0.2.6
Summary: Chat with your documents offline using AI.
Home-page: https://github.com/marella/chatdocs
Author: Ravindra Marella
Author-email: mv.ravindra007@gmail.com
License: MIT
Keywords: chatdocs ctransformers transformers langchain chroma ai llm
Platform: UNKNOWN
Classifier: Development Status :: 1 - Planning
Classifier: Intended Audience :: Developers
Classifier: Intended Audience :: Education
Classifier: Intended Audience :: Science/Research
Classifier: License :: OSI Approved :: MIT License
Classifier: Programming Language :: Python :: 3
Classifier: Topic :: Scientific/Engineering
Classifier: Topic :: Scientific/Engineering :: Mathematics
Classifier: Topic :: Scientific/Engineering :: Artificial Intelligence
Classifier: Topic :: Software Development
Classifier: Topic :: Software Development :: Libraries
Classifier: Topic :: Software Development :: Libraries :: Python Modules
Requires-Dist: InstructorEmbedding (<2.0.0,>=1.0.1)
Requires-Dist: accelerate (>=0.20.3)
Requires-Dist: argilla (==1.8.0)
Requires-Dist: chromadb (<0.4.0,>=0.3.0)
Requires-Dist: ctransformers (<0.3.0,>=0.2.25)
Requires-Dist: deepmerge (<2.0.0,>=1.1.0)
Requires-Dist: extract-msg (<0.42.0,>=0.41.0)
Requires-Dist: langchain (>=0.0.181)
Requires-Dist: pandoc (<3.0.0,>=2.3)
Requires-Dist: pdfminer.six (==20221105)
Requires-Dist: pydantic (<2.0,>=1.9)
Requires-Dist: pypandoc (<2.0.0,>=1.11)
Requires-Dist: pyyaml (>=6.0)
Requires-Dist: quart (<0.19.0,>=0.18.3)
Requires-Dist: sentence-transformers (<3.0.0,>=2.2.2)
Requires-Dist: tqdm (<5.0.0,>=4.64.1)
Requires-Dist: transformers (>=4.32.0)
Requires-Dist: typer (>=0.9.0)
Requires-Dist: typing-extensions (<5.0.0,>=4.4.0)
Requires-Dist: unstructured (<0.7.0,>=0.6.0)
Provides-Extra: gptq
Requires-Dist: auto-gptq (<0.5.0,>=0.4.2) ; extra == 'gptq'
Requires-Dist: optimum (>=1.12.0) ; extra == 'gptq'
Provides-Extra: tests
Requires-Dist: pytest ; extra == 'tests'
